ttsds/__about__.py
ttsds/__init__.py
ttsds/ttsds.py
ttsds/benchmarks/__init__.py
ttsds/benchmarks/benchmark.py
ttsds/benchmarks/environment/voicerestore.py
ttsds/benchmarks/environment/wada_snr.py
ttsds/benchmarks/general/hubert.py
ttsds/benchmarks/general/mhubert.py
ttsds/benchmarks/general/wav2vec2.py
ttsds/benchmarks/general/wav2vec2_xlsr.py
ttsds/benchmarks/general/wavlm.py
ttsds/benchmarks/intelligibility/mwhisper_activations.py
ttsds/benchmarks/intelligibility/w2v2_activations.py
ttsds/benchmarks/intelligibility/w2v2_xlsr_activations.py
ttsds/benchmarks/intelligibility/whisper_activations.py
ttsds/benchmarks/prosody/allosaurus.py
ttsds/benchmarks/prosody/hubert_token.py
ttsds/benchmarks/prosody/mhubert_token.py
ttsds/benchmarks/prosody/mpm.py
ttsds/benchmarks/prosody/pitch.py
ttsds/benchmarks/speaker/dvector.py
ttsds/benchmarks/speaker/wespeaker.py
ttsds/dvector/README.md
ttsds/dvector/dvector.pt
ttsds/util/__init__.py
ttsds/util/cache.py
ttsds/util/dataset.py
ttsds/util/distances.py
ttsds/util/measures.py
ttsds/util/mpm.py
ttsds/util/mpm_modules.py
ttsds/util/parallel_distances.py
ttsds-2.1.1.dist-info/METADATA
ttsds-2.1.1.dist-info/WHEEL
ttsds-2.1.1.dist-info/RECORD
