Metadata-Version: 2.4
Name: ttsds
Version: 2.1.1
Project-URL: Documentation, https://github.com/ttsds/ttsds#readme
Project-URL: Issues, https://github.com/ttsds/ttsds/issues
Project-URL: Source, https://github.com/ttsds/ttsds
Author-email: Christoph Minixhofer <christoph.minixhofer@gmail.com>
License-Expression: MIT
Classifier: Development Status :: 4 - Beta
Classifier: Programming Language :: Python
Classifier: Programming Language :: Python :: 3.8
Classifier: Programming Language :: Python :: 3.9
Classifier: Programming Language :: Python :: 3.10
Classifier: Programming Language :: Python :: 3.11
Classifier: Programming Language :: Python :: 3.12
Classifier: Programming Language :: Python :: Implementation :: CPython
Classifier: Programming Language :: Python :: Implementation :: PyPy
Requires-Python: >=3.8
Requires-Dist: allosaurus>=1.0.0
Requires-Dist: jiwer>=2.2.0
Requires-Dist: librosa>=0.10.0
Requires-Dist: numpy>=1.21.0
Requires-Dist: openai-whisper==20240927
Requires-Dist: pandas>=1.3.0
Requires-Dist: pesq>=0.0.1
Requires-Dist: phonemizer>=3.0.0
Requires-Dist: pyannote-audio==3.1.*
Requires-Dist: pyworld>=0.2.0
Requires-Dist: rich>=13.0.0
Requires-Dist: silero-vad==5.1
Requires-Dist: statsmodels>=0.12.0
Requires-Dist: torch>=2.0.0
Requires-Dist: transformers>=4.0.0
Requires-Dist: voicerestore-fork>=0.1.0
Requires-Dist: wespeaker-unofficial>=0.0.1
